[
    {
        "productName": "Adobe After Effects",
        "productIndices": [
            {
                "indexName": "after-effects",
                "indexPathPrefix": "/after-effects/"
            }
        ]
    },
    {
        "productName": "Adobe Analytics",
        "productIndices": [
            {
                "indexName": "analytics-2.0-apis",
                "indexPathPrefix": "/analytics-apis/docs/2.0/"
            }
        ]
    },
    {
        "productName": "Adobe Animate",
        "productIndices": [
            {
                "indexName": "animate",
                "indexPathPrefix": "/animate/"
            }
        ]
    },
    {
        "productName": "Adobe Photoshop",
        "productIndices": [
            {
                "indexName": "photoshop",
                "indexPathPrefix": "/photoshop/"
            },
            {
                "indexName": "uxp-photoshop",
                "indexPathPrefix": "/photoshop/uxp/2022/"
            },
            {
                "indexName": "uxp-photoshop-2021",
                "indexPathPrefix": "/photoshop/uxp/2021/"
            },
            {
                "indexName": "cis-photoshop-api-docs",
                "indexPathPrefix": "/photoshop/photoshop-api-docs/"
            },
            {
                "indexName": "photoshop-api",
                "indexPathPrefix": "/photoshop/api/"
            }
        ]
    },
    {
        "productName": "Adobe Substance 3D",
        "productIndices": [
            {
                "indexName": "substance-3d-automation",
                "indexPathPrefix": "/substance-3d-automation/docs/"
            },
            {
                "indexName": "franklin-substance-3d-automation",
                "indexPathPrefix": "/substance-3d-automation/"
            },
            {
                "indexName": "franklin-substance-3d",
                "indexPathPrefix": "/substance3d/"
            },
            {
                "indexName": "franklin-substance-3d-sdk",
                "indexPathPrefix": "/substance3d-sdk/"
            }
        ]
    },
    {
        "productName": "Adobe I/O",
        "productIndices": [
            {
                "indexName": "adobe-io-events",
                "indexPathPrefix": "/events/docs/"
            },
            {
                "indexName": "franklin-adobe-io-events",
                "indexPathPrefix": "/events/"
            },
            {
                "indexName": "adobe-io-runtime",
                "indexPathPrefix": "/runtime/docs"
            },
            {
                "indexName": "franklin-adobe-io-runtime",
                "indexPathPrefix": "/runtime/"
            }
        ]
    },
    {
        "productName": "Adobe Developer Console",
        "productIndices": [
            {
                "indexName": "adobe-dev-console",
                "indexPathPrefix": "/developer-console/docs/"
            },
            {
                "indexName": "franklin-adobe-dev-console",
                "indexPathPrefix": "/developer-console/"
            }
        ]
    },
    {
        "productName": "Adobe Developer App Builder",
        "productIndices": [
            {
                "indexName": "app-builder",
                "indexPathPrefix": "/app-builder/docs/"
            },
            {
                "indexName": "app-builder-template-registry",
                "indexPathPrefix": "/app-builder-template-registry/"
            },
            {
                "indexName": "graphql-mesh-gateway",
                "indexPathPrefix": "/graphql-mesh-gateway/"
            },
            {
                "indexName": "franklin-app-builder",
                "indexPathPrefix": "/app-builder/"
            }
        ]
    },
    {
        "productName": "Adobe Lightroom",
        "productIndices": [
            {
                "indexName": "franklin-lightroom",
                "indexPathPrefix": "/lightroom/"
            },
            {
                "indexName": "lightroom-public-apis",
                "indexPathPrefix": "/lightroom/lightroom-api-docs/"
            },
            {
                "indexName": "lightroom-classic",
                "indexPathPrefix": "/lightroom-classic/"
            }
        ]
    },
    {
        "productName": "Adobe Document Services",
        "productIndices": [
            {
                "indexName": "franklin-sign-api",
                "indexPathPrefix": "/adobesign-api/"
            },
            {
                "indexName": "document-services",
                "indexPathPrefix": "/document-services/"
            },
            {
                "indexName": "pdfservices-api-documentation",
                "indexPathPrefix": "/document-services/docs/"
            }
        ]
    },
    {
        "productName": "Adobe Commerce",
        "productIndices": [
            {
                "indexName": "franklin-commerce",
                "indexPathPrefix": "/commerce/"
            },
            {
                "indexName": "commerce-webapi",
                "indexPathPrefix": "/commerce/webapi/"
            },
            {
                "indexName": "commerce-frontend-core",
                "indexPathPrefix": "/commerce/frontend-core/"
            },
            {
                "indexName": "commerce-services",
                "indexPathPrefix": "/commerce/services/"
            }
        ]
    },
    {
        "productName": "Adobe Experience Manager",
        "productIndices": [
            {
                "indexName": "franklin-umapi",
                "indexPathPrefix": "/umapi/"
            },
            {
                "indexName": "franklin-audience-manager",
                "indexPathPrefix": "/audience-manager/"
            }
        ]
    },
    {
        "productName": "Adobe Experience Platform",
        "productIndices": [
            {
                "indexName": "aep-mobile-sdkdocs",
                "indexPathPrefix": "/client-sdks/"
            }
        ]
    }
        
]
